emplode/__init__.py
emplode/computer_use/__init__.py
emplode/computer_use/loop.py
emplode/computer_use/tools/__init__.py
emplode/computer_use/tools/base.py
emplode/computer_use/tools/bash.py
emplode/computer_use/tools/collection.py
emplode/computer_use/tools/computer.py
emplode/computer_use/tools/edit.py
emplode/computer_use/tools/run.py
emplode/computer_use/unused_markdown.py
emplode/core/__init__.py
emplode/core/archived_server_1.py
emplode/core/archived_server_2.py
emplode/core/async_core.py
emplode/core/computer/__init__.py
emplode/core/computer/ai/__init__.py
emplode/core/computer/ai/ai.py
emplode/core/computer/browser/__init__.py
emplode/core/computer/browser/browser.py
emplode/core/computer/browser/browser_next.py
emplode/core/computer/calendar/__init__.py
emplode/core/computer/calendar/calendar.py
emplode/core/computer/clipboard/__init__.py
emplode/core/computer/clipboard/clipboard.py
emplode/core/computer/computer.py
emplode/core/computer/contacts/__init__.py
emplode/core/computer/contacts/contacts.py
emplode/core/computer/display/__init__.py
emplode/core/computer/display/display.py
emplode/core/computer/display/point/point.py
emplode/core/computer/docs/__init__.py
emplode/core/computer/docs/docs.py
emplode/core/computer/files/__init__.py
emplode/core/computer/files/files.py
emplode/core/computer/keyboard/__init__.py
emplode/core/computer/keyboard/keyboard.py
emplode/core/computer/mail/__init__.py
emplode/core/computer/mail/mail.py
emplode/core/computer/mouse/__init__.py
emplode/core/computer/mouse/mouse.py
emplode/core/computer/os/__init__.py
emplode/core/computer/os/os.py
emplode/core/computer/skills/skills.py
emplode/core/computer/sms/__init__.py
emplode/core/computer/sms/sms.py
emplode/core/computer/terminal/__init__.py
emplode/core/computer/terminal/base_language.py
emplode/core/computer/terminal/languages/__init__.py
emplode/core/computer/terminal/languages/applescript.py
emplode/core/computer/terminal/languages/html.py
emplode-0.7.dist-info/METADATA
emplode-0.7.dist-info/WHEEL
emplode-0.7.dist-info/entry_points.txt
emplode-0.7.dist-info/RECORD
